jaqk/__init__.py
jaqk/exceptions.py
jaqk/setup.py
jaqk/test2.py
jaqk/Spyder/__init__.py
jaqk/Spyder/datefile.py
jaqk/Spyder/dates_temp.py
jaqk/Spyder/getter.py
jaqk/Spyder/main_loop.py
jaqk/Spyder/parse_main.py
jaqk/Spyder/parsers.py
jaqk/Spyder/test_Spyder.py
jaqk/Spyder/update_main.py
jaqk/calculations/__init__.py
jaqk/calculations/rank.py
jaqk/calculations/test_calculations.py
jaqk/database/__init__.py
jaqk/database/AAPL/AAPL_Description.py
jaqk/database/AAPL/AAPL_EPS_Revisions.py
jaqk/database/AAPL/AAPL_EPS_Trend.py
jaqk/database/AAPL/AAPL_Earnings_Estimate.py
jaqk/database/AAPL/AAPL_Earnings_History.py
jaqk/database/AAPL/AAPL_Executives.py
jaqk/database/AAPL/AAPL_Financial_Highlights.py
jaqk/database/AAPL/AAPL_Growth_Estimates.py
jaqk/database/AAPL/AAPL_Revenue_Estimate.py
jaqk/database/AAPL/AAPL_Summary.py
jaqk/database/AAPL/AAPL_Trading_Information.py
jaqk/database/AAPL/AAPL_Valuation_Measures.py
jaqk/database/AAPL/AAPL_balance.py
jaqk/database/AAPL/AAPL_cash_flow.py
jaqk/database/AAPL/AAPL_income.py
jaqk/database/AAPL/AAPL_major_holders.py
jaqk/database/AAPL/AAPL_price_daily.py
jaqk/database/AAPL/AAPL_price_monthly.py
jaqk/database/AAPL/AAPL_price_weekly.py
jaqk/database/AAPL/AAPL_top_institutional_holders.py
jaqk/database/AAPL/AAPL_top_mutual_fund_holders.py
jaqk/database/AAPL/__init__.py
jaqk/database/AMZN/AMZN_Description.py
jaqk/database/AMZN/AMZN_EPS_Revisions.py
jaqk/database/AMZN/AMZN_EPS_Trend.py
jaqk/database/AMZN/AMZN_Earnings_Estimate.py
jaqk/database/AMZN/AMZN_Earnings_History.py
jaqk/database/AMZN/AMZN_Executives.py
jaqk/database/AMZN/AMZN_Financial_Highlights.py
jaqk/database/AMZN/AMZN_Growth_Estimates.py
jaqk/database/AMZN/AMZN_Revenue_Estimate.py
jaqk/database/AMZN/AMZN_Summary.py
jaqk/database/AMZN/AMZN_Trading_Information.py
jaqk/database/AMZN/AMZN_Valuation_Measures.py
jaqk/database/AMZN/AMZN_balance.py
jaqk/database/AMZN/AMZN_cash_flow.py
jaqk/database/AMZN/AMZN_income.py
jaqk/database/AMZN/AMZN_major_holders.py
JAQK-0.0.3.1.0.dist-info/LICENSE
JAQK-0.0.3.1.0.dist-info/METADATA
JAQK-0.0.3.1.0.dist-info/WHEEL
JAQK-0.0.3.1.0.dist-info/top_level.txt
JAQK-0.0.3.1.0.dist-info/RECORD
