Metadata-Version: 2.1
Name: JAQK
Version: 0.0.3.1.0
Summary: A light toolkit for crawling financia data and basic analysis and calcualtions.
Home-page: https://github.com/Haannbboo/JAQK
Author: Hanbo Guo
Author-email: hbopublic@163.com
License: MIT
Keywords: US Stock Market Data
Platform: UNKNOWN
Classifier: Programming Language :: Python :: 3.4
Classifier: Programming Language :: Python :: 3.5
Classifier: Programming Language :: Python :: 3.6
Classifier: Programming Language :: Python :: 3.7
Classifier: License :: OSI Approved :: MIT License
Requires-Dist: pandas (>=0.21.0)
Requires-Dist: requests (>=2.1.0)
Requires-Dist: numpy (>=1.14.0)
Requires-Dist: pyquery (>=1.4.0)
Requires-Dist: aiohttp (>=3.4.0)
Requires-Dist: PySimpleGUI (>=3.0.0)
Requires-Dist: scipy (>=1.0.0)
Requires-Dist: openpyxl (>=2.4.0)
Requires-Dist: xlrd (>=1.0.0)
